html_cleaner.py
html_cleaner-0.4.dev0.dist-info/METADATA
html_cleaner-0.4.dev0.dist-info/WHEEL
html_cleaner-0.4.dev0.dist-info/entry_points.txt
html_cleaner-0.4.dev0.dist-info/top_level.txt
html_cleaner-0.4.dev0.dist-info/RECORD
