Metadata-Version: 2.1
Name: html-cleaner
Version: 0.4.dev0
Summary: clean up html files
Home-page: https://github.com/account-login/html_cleaner
Author: account-login
Author-email: UNKNOWN
License: MIT
Keywords: html cleaner tidy
Platform: UNKNOWN
Classifier: Development Status :: 3 - Alpha
Classifier: License :: OSI Approved :: MIT License
Classifier: Operating System :: OS Independent
Classifier: Programming Language :: Python :: 3 :: Only
Requires-Dist: beautifulsoup4
Requires-Dist: html5lib
